pdf2tex/__init__.py
pdf2tex/cli.py
pdf2tex/config.py
pdf2tex/api/__init__.py
pdf2tex/api/app.py
pdf2tex/chunking/__init__.py
pdf2tex/chunking/chapter_detector.py
pdf2tex/chunking/models.py
pdf2tex/chunking/service.py
pdf2tex/chunking/splitter.py
pdf2tex/extraction/__init__.py
pdf2tex/extraction/math_extractor.py
pdf2tex/extraction/models.py
pdf2tex/extraction/ocr.py
pdf2tex/extraction/pdf_parser.py
pdf2tex/extraction/service.py
pdf2tex/generation/__init__.py
pdf2tex/generation/llm.py
pdf2tex/generation/prompts.py
pdf2tex/generation/service.py
pdf2tex/generation/validator.py
pdf2tex/pipeline/__init__.py
pdf2tex/pipeline/orchestrator.py
pdf2tex/pipeline/state.py
pdf2tex/pipeline/workers.py
pdf2tex/rag/__init__.py
pdf2tex/rag/embeddings.py
pdf2tex/rag/reranker.py
pdf2tex/rag/service.py
pdf2tex/rag/vectorstore.py
pdf2tex-0.2.0.dist-info/METADATA
pdf2tex-0.2.0.dist-info/WHEEL
pdf2tex-0.2.0.dist-info/entry_points.txt
pdf2tex-0.2.0.dist-info/RECORD
