Metadata-Version: 2.4
Name: pdf2tex
Version: 0.2.0
Summary: High-performance RAG-based PDF to LaTeX conversion module
Project-URL: Documentation, https://github.com/pdf2tex/pdf2tex#readme
Project-URL: Repository, https://github.com/pdf2tex/pdf2tex
Project-URL: Issues, https://github.com/pdf2tex/pdf2tex/issues
Author: PDF2TeX Team
License-Expression: MIT
Keywords: document-conversion,latex,llm,ocr,pdf,rag
Classifier: Development Status :: 3 - Alpha
Classifier: Intended Audience :: Developers
Classifier: Intended Audience :: Science/Research
Classifier: License :: OSI Approved :: MIT License
Classifier: Programming Language :: Python :: 3
Classifier: Programming Language :: Python :: 3.11
Classifier: Programming Language :: Python :: 3.12
Classifier: Topic :: Scientific/Engineering
Classifier: Topic :: Text Processing :: Markup :: LaTeX
Requires-Python: >=3.11
Requires-Dist: aiofiles>=23.2.0
Requires-Dist: alembic>=1.13.0
Requires-Dist: asyncpg>=0.29.0
Requires-Dist: fastapi>=0.111.0
Requires-Dist: httpx>=0.27.0
Requires-Dist: huggingface-hub>=0.23.0
Requires-Dist: jinja2>=3.1.0
Requires-Dist: marker-pdf>=0.2.0
Requires-Dist: minio>=7.2.0
Requires-Dist: nougat-ocr>=0.1.0
Requires-Dist: numpy>=1.26.0
Requires-Dist: paddleocr>=2.7.0
Requires-Dist: paddlepaddle>=2.6.0
Requires-Dist: pdf2image>=1.16.0
Requires-Dist: pydantic-settings>=2.2.0
Requires-Dist: pydantic>=2.7.0
Requires-Dist: pymupdf>=1.24.0
Requires-Dist: python-multipart>=0.0.9
Requires-Dist: qdrant-client>=1.9.0
Requires-Dist: ray[default]>=2.20.0
Requires-Dist: redis>=5.0.0
Requires-Dist: rich>=13.7.0
Requires-Dist: sentence-transformers>=2.7.0
Requires-Dist: sqlalchemy>=2.0.0
Requires-Dist: structlog>=24.1.0
Requires-Dist: tenacity>=8.3.0
Requires-Dist: torch>=2.2.0
Requires-Dist: transformers>=4.40.0
Requires-Dist: typer>=0.12.0
Requires-Dist: uvicorn[standard]>=0.29.0
Provides-Extra: dev
Requires-Dist: ipython>=8.24.0; extra == 'dev'
Requires-Dist: mypy>=1.10.0; extra == 'dev'
Requires-Dist: pre-commit>=3.7.0; extra == 'dev'
Requires-Dist: pytest-asyncio>=0.23.0; extra == 'dev'
Requires-Dist: pytest-cov>=5.0.0; extra == 'dev'
Requires-Dist: pytest>=8.0.0; extra == 'dev'
Requires-Dist: ruff>=0.4.0; extra == 'dev'
